setup.py
pongo/__init__.py
pongo/config.py
pongo/controller.py
pongo/model.py
pongo/server.py
pongo.egg-info/PKG-INFO
pongo.egg-info/SOURCES.txt
pongo.egg-info/dependency_links.txt
pongo.egg-info/requires.txt
pongo.egg-info/top_level.txt
pongo/conf/default.ini
pongo/static/css/reset.css
pongo/static/css/style.css
pongo/static/img/bg.png
pongo/static/js/jquery-1.3.2.min.js
pongo/static/js/local.js
pongo/views/collections.tpl
pongo/views/databases.tpl
pongo/views/documents.tpl
pongo/views/footer.tpl
pongo/views/guess.tpl
pongo/views/header.tpl
pongo/views/home.tpl
pongo/views/utils.tpl