Metadata-Version: 1.0
Name: pongo
Version: 0.1.2
Summary: A Mongo database explorer
Home-page: http://bitbucket.org/vrde/pongo
Author: Alberto Granzotto (vrde)
Author-email: vrde@tastybra.in
License: UNKNOWN
Platform: UNKNOWN
Classifier: Development Status :: 3 - Alpha
Classifier: Intended Audience :: Developers
Classifier: License :: OSI Approved :: BSD License
Classifier: Operating System :: OS Independent
Classifier: Programming Language :: Python
